noisyduck/__init__.py
noisyduck/cli.py
noisyduck/io.py
noisyduck/noisyduck.py
noisyduck/annulus/__init__.py
noisyduck/annulus/analytical.py
noisyduck/annulus/numerical.py
noisyduck/filter/__init__.py
noisyduck/filter/filter.py
noisyduck-0.2.1.dist-info/DESCRIPTION.rst
noisyduck-0.2.1.dist-info/METADATA
noisyduck-0.2.1.dist-info/RECORD
noisyduck-0.2.1.dist-info/WHEEL
noisyduck-0.2.1.dist-info/entry_points.txt
noisyduck-0.2.1.dist-info/metadata.json
noisyduck-0.2.1.dist-info/top_level.txt
tests/__init__.py
tests/test_annulus.py
tests/test_cli.py
