Metadata-Version: 2.0
Name: noisyduck
Version: 0.2.1
Summary: A python tool for computing eigenmode decompositions of duct flows.
Home-page: https://github.com/nwukie/noisyduck
Author: Nathan Wukie
Author-email: nathan.wukie@gmail.com
License: BSD license
Keywords: noisyduck
Platform: UNKNOWN
Classifier: Development Status :: 2 - Pre-Alpha
Classifier: Intended Audience :: Developers
Classifier: License :: OSI Approved :: BSD License
Classifier: Natural Language :: English
Classifier: Programming Language :: Python :: 2
Classifier: Programming Language :: Python :: 2.6
Classifier: Programming Language :: Python :: 2.7
Classifier: Programming Language :: Python :: 3
Classifier: Programming Language :: Python :: 3.3
Classifier: Programming Language :: Python :: 3.4
Classifier: Programming Language :: Python :: 3.5
Requires-Dist: Click (>=6.0)
Requires-Dist: numpy (>=1.7)
Requires-Dist: scipy
Requires-Dist: matplotlib
